setup.py
client/__init__.py
client/client.py
client/client/__init__.py
client/client/add_contact.py
client/client/database.py
client/client/del_contact.py
client/client/main_window.py
client/client/main_window_ui.py
client/client/start_dialog.py
client/client/transport.py
client/common/__init__.py
client/common/decorators.py
client/common/descriptors.py
client/common/errors.py
client/common/metaclasses.py
client/common/utils.py
client/common/variables.py
client/log/__init__.py
client/log/client_log_config.py
client/log/server_log_config.py
client/unit_test/__init__.py
client/unit_test/test_client.py
client/unit_test/test_server.py
client/unit_test/test_utils.py
mess_client_skif.egg-info/PKG-INFO
mess_client_skif.egg-info/SOURCES.txt
mess_client_skif.egg-info/dependency_links.txt
mess_client_skif.egg-info/requires.txt
mess_client_skif.egg-info/top_level.txt